{
  "main_niche": "Relationship (সম্পর্ক)",
  "sub_niches": [
    {"id": "marriage", "bn": "সুখী বিবাহিত জীবন", "en": "Happy Marriage", "demand": "High"},
    {"id": "communication", "bn": "দাম্পত্য যোগাযোগ", "en": "Couple Communication", "demand": "High"},
    {"id": "trust-rebuild", "bn": "বিশ্বাস পুনর্গঠন", "en": "Rebuilding Trust", "demand": "Medium"},
    {"id": "conflict", "bn": "দ্বন্দ্ব নিরসন", "en": "Conflict Resolution", "demand": "Medium"},
    {"id": "parenting", "bn": "সন্তান লালনপালন", "en": "Parenting", "demand": "High"},
    {"id": "teen-parenting", "bn": "কিশোর সন্তানের সাথে সম্পর্ক", "en": "Parenting Teens", "demand": "Medium"},
    {"id": "self-love", "bn": "আত্মভালোবাসা", "en": "Self-Love", "demand": "High"},
    {"id": "self-confidence", "bn": "আত্মবিশ্বাস বাড়ানো", "en": "Building Self-Confidence", "demand": "High"},
    {"id": "boundaries", "bn": "সীমানা নির্ধারণ", "en": "Setting Boundaries", "demand": "Medium"},
    {"id": "toxic-relationship", "bn": "বিষাক্ত সম্পর্ক থেকে মুক্তি", "en": "Toxic Relationship Recovery", "demand": "High"},
    {"id": "breakup", "bn": "ব্রেকআপ থেকে সামলানো", "en": "Breakup Recovery", "demand": "High"},
    {"id": "loneliness", "bn": "একাকীত্ব দূর করা", "en": "Overcoming Loneliness", "demand": "Medium"},
    {"id": "social-skills", "bn": "সামাজিক দক্ষতা", "en": "Social Skills", "demand": "Medium"},
    {"id": "friendship", "bn": "বন্ধুত্ব গড়ে তোলা", "en": "Building Friendships", "demand": "Low"},
    {"id": "family", "bn": "পারিবারিক সম্পর্ক", "en": "Family Relationships", "demand": "Medium"},
    {"id": "in-laws", "bn": "শ্বশুরবাড়ির সম্পর্ক", "en": "In-Law Relations", "demand": "High"},
    {"id": "emotional-intelligence", "bn": "আবেগীয় বুদ্ধিমত্তা", "en": "Emotional Intelligence", "demand": "Medium"},
    {"id": "anger-management", "bn": "রাগ নিয়ন্ত্রণ", "en": "Anger Management", "demand": "Medium"},
    {"id": "forgiveness", "bn": "ক্ষমা করা শেখা", "en": "Learning to Forgive", "demand": "Medium"},
    {"id": "dating", "bn": "ডেটিং ও সম্পর্ক শুরু", "en": "Dating & New Relationships", "demand": "Medium"},
    {"id": "long-distance", "bn": "দূরত্বের সম্পর্ক", "en": "Long-Distance Relationships", "demand": "Medium"},
    {"id": "intimacy", "bn": "ঘনিষ্ঠতা বাড়ানো", "en": "Building Intimacy", "demand": "Medium"},
    {"id": "codependency", "bn": "পরনির্ভরশীলতা কাটানো", "en": "Overcoming Codependency", "demand": "Low"},
    {"id": "attachment", "bn": "অ্যাটাচমেন্ট স্টাইল", "en": "Attachment Styles", "demand": "Medium"},
    {"id": "empathy", "bn": "সহানুভূতি বাড়ানো", "en": "Building Empathy", "demand": "Low"},
    {"id": "workplace-relations", "bn": "কর্মক্ষেত্রে সম্পর্ক", "en": "Workplace Relationships", "demand": "Medium"},
    {"id": "leadership", "bn": "নেতৃত্বের দক্ষতা", "en": "Leadership Skills", "demand": "Medium"},
    {"id": "people-pleasing", "bn": "মানুষকে খুশি করার অভ্যাস", "en": "People Pleasing", "demand": "Medium"},
    {"id": "body-image", "bn": "শরীরের ইমেজ", "en": "Body Image", "demand": "Medium"},
    {"id": "grief", "bn": "শোক সামলানো", "en": "Grief Recovery", "demand": "Low"}
  ]
}
